bsonschema/__init__.py
bsonschema/__main__.py
bsonschema/_format.py
bsonschema/_keywords.py
bsonschema/_legacy_keywords.py
bsonschema/_types.py
bsonschema/_utils.py
bsonschema/exceptions.py
bsonschema/validators.py
bsonschema-1.0.7.dist-info/LICENSE
bsonschema-1.0.7.dist-info/METADATA
bsonschema-1.0.7.dist-info/WHEEL
bsonschema-1.0.7.dist-info/top_level.txt
bsonschema-1.0.7.dist-info/RECORD
